include/genpybind/genpybind.h
include/genpybind/binding-helpers.h
genpybind-0.5.0.dist-info/RECORD
genpybind-0.5.0.dist-info/entry_points.txt
genpybind-0.5.0.dist-info/METADATA
genpybind-0.5.0.dist-info/WHEEL
genpybind-0.5.0.dist-info/licenses/LICENSES/LicenseRef-LLVM.txt
genpybind-0.5.0.dist-info/licenses/LICENSES/MIT.txt
bin/genpybind-tool
share/cmake/genpybind/genpybind.cmake
share/cmake/genpybind/genpybindConfigVersion.cmake
share/cmake/genpybind/genpybindConfig.cmake
share/cmake/genpybind/genpybindTargets.cmake
share/cmake/genpybind/genpybindTargets-release.cmake
genpybind/__init__.py
