Metadata-Version: 2.1
Name: genpybind
Version: 0.5.0
Summary: Autogeneration of pybind11 Python bindings from manually annotated C++ headers
Keywords: C++,Python bindings,pybind11
Author-Email: =?utf-8?q?Johann_Kl=C3=A4hn?= <genpybind@jklaehn.de>
Classifier: Development Status :: 4 - Beta
Classifier: License :: OSI Approved :: MIT License
Classifier: Intended Audience :: Developers
Classifier: Topic :: Software Development :: Libraries :: Python Modules
Classifier: Topic :: Utilities
Classifier: Programming Language :: Python :: 3 :: Only
Classifier: Programming Language :: C++
Project-URL: Homepage, https://github.com/kljohann/genpybind
Project-URL: Repository, https://github.com/kljohann/genpybind
Project-URL: Issues, https://github.com/kljohann/genpybind/issues
